tsportfo/__init__.py
tsportfo-0.1.0.dist-info/METADATA
tsportfo-0.1.0.dist-info/WHEEL
tsportfo-0.1.0.dist-info/RECORD
