Metadata-Version: 2.1
Name: tsportfo
Version: 0.1.0
Summary: The description not yet provided.
Author: Saeed Foroutan
Author-email: foroutansaeed@gmail.com
Requires-Python: >=3.12,<4.0
Classifier: Programming Language :: Python :: 3
Classifier: Programming Language :: Python :: 3.12
